Operaciones.cp312-win_amd64.pyd
documentos.py
pycalcpp.py
pycalcpp-0.2.0.dist-info/METADATA
pycalcpp-0.2.0.dist-info/WHEEL
pycalcpp-0.2.0.dist-info/top_level.txt
pycalcpp-0.2.0.dist-info/RECORD
